__init__.py
main.py
spyglass.py
spyglass_py-0.0.4.dist-info/METADATA
spyglass_py-0.0.4.dist-info/WHEEL
spyglass_py-0.0.4.dist-info/licenses/LICENSE
spyglass_py-0.0.4.dist-info/RECORD
