Metadata-Version: 2.1
Name: spyglass-py
Version: 0.0.4
Summary: Spyglass python library.
Project-URL: Homepage, https://spyglass.software
Author-email: Tyler Julian <tyler@spyglass.software>
License-File: LICENSE
Classifier: License :: OSI Approved :: MIT License
Classifier: Operating System :: OS Independent
Classifier: Programming Language :: Python :: 3
Requires-Python: >=3.7
